{
  "measure": {
    "SessionKey": "2021R1",
    "MeasurePrefix": "SB",
    "MeasureNumber": 167,
    "CatchLine": "Provides that assessed value of property may be value determined to be necessary to effect fairness and equity in assessed values of property and property in same area in same property class, provided value so determined is not greater than maximum assessed value or real market value of property.",
    "MinorityCatchLine": null,
    "MeasureSummary": "\tProvides that assessed value of property may be value determined to be necessary to effect fairness and equity in assessed values of property and property in same area in same property class, provided value so determined is not greater than maximum assessed value or real market value of property. \n\tTakes effect on 91st day following adjournment sine die.",
    "CurrentVersion": null,
    "RelatingToFull": "Relating to the assessment of property for purposes of ad valorem property taxation; creating new provisions; amending ORS 307.032, 308.146, 308.153 and 308.156; and prescribing an effective date.\n\t",
    "RelatingTo": "Relating to the assessment of property for purposes of ad valorem property taxation; prescribing an effective date.",
    "AtTheRequestOf": "(at the request of Bert Dunn)",
    "ChapterNumber": null,
    "CurrentLocation": "In Senate Committee",
    "CurrentCommitteeCode": "SFR",
    "CurrentSubCommittee": null,
    "FiscalImpact": "May have fiscal impact, but no statement yet issued",
    "RevenueImpact": "May have revenue impact, but no statement yet issued",
    "EmergencyClause": false,
    "EffectiveDate": null,
    "FiscalAnalyst": "Michael Graham",
    "RevenueEconomist": "Jaime McGovern",
    "LCNumber": 384,
    "Vetoed": false,
    "CreatedDate": "2020-12-14T12:16:48",
    "ModifiedDate": "2021-01-21T09:19:15",
    "PrefixMeaning": "Senate Bill"
  },
  "sponsors": [
    {
      "MeasureSponsorId": "112297",
      "SessionKey": "2021R1",
      "MeasurePrefix": "SB",
      "MeasureNumber": 167,
      "SponsorType": "Presession",
      "LegislatoreCode": null,
      "CommitteeCode": null,
      "SponsorLevel": "Regular",
      "PrintOrder": "20",
      "PresessionFiledMessage": "(Presession filed.)",
      "CreatedDate": "2021-01-09T19:30:30",
      "ModifiedDate": null
    },
    {
      "MeasureSponsorId": "112298",
      "SessionKey": "2021R1",
      "MeasurePrefix": "SB",
      "MeasureNumber": 167,
      "SponsorType": "Member",
      "LegislatoreCode": "Sen Beyer",
      "CommitteeCode": null,
      "SponsorLevel": "Chief",
      "PrintOrder": "1",
      "PresessionFiledMessage": null,
      "CreatedDate": "2021-01-09T19:30:30",
      "ModifiedDate": null
    }
  ],
  "historyActions": [
    {
      "MeasureHistoryId": 493260,
      "SessionKey": "2021R1",
      "MeasurePrefix": "SB",
      "MeasureNumber": 167,
      "Chamber": "S",
      "ActionDate": "2021-01-11T09:28:22",
      "ActionText": "Introduction and first reading. Referred to President's desk.",
      "VoteText": null,
      "CreatedDate": "2021-01-11T09:28:41",
      "ModifiedDate": null,
      "PublicNotification": true
    },
    {
      "MeasureHistoryId": 494083,
      "SessionKey": "2021R1",
      "MeasurePrefix": "SB",
      "MeasureNumber": 167,
      "Chamber": "S",
      "ActionDate": "2021-01-19T11:35:42",
      "ActionText": "Referred to Finance and Revenue.",
      "VoteText": null,
      "CreatedDate": "2021-01-19T11:36:35",
      "ModifiedDate": null,
      "PublicNotification": true
    },
    {
      "MeasureHistoryId": 536308,
      "SessionKey": "2021R1",
      "MeasurePrefix": "SB",
      "MeasureNumber": 167,
      "Chamber": "S",
      "ActionDate": "2021-06-26T17:37:00",
      "ActionText": "In committee upon adjournment.",
      "VoteText": null,
      "CreatedDate": "2021-07-06T13:57:54",
      "ModifiedDate": null,
      "PublicNotification": false
    }
  ],
  "documents": [
    {
      "SessionKey": "2021R1",
      "MeasurePrefix": "SB",
      "MeasureNumber": 167,
      "VersionDescription": "Introduced",
      "DocumentUrl": "https://olis.oregonlegislature.gov/liz/2021R1/Downloads/MeasureDocument/SB167/Introduced",
      "CreatedDate": "2021-01-10T08:18:41.5",
      "ModifiedDate": null
    }
  ],
  "testimony": []
}