{
  "measure": {
    "SessionKey": "2021R1",
    "MeasurePrefix": "SB",
    "MeasureNumber": 82,
    "CatchLine": "Establishes Individual Development Account Fund.",
    "MinorityCatchLine": null,
    "MeasureSummary": "\tEstablishes Individual Development Account Fund. Continuously appropriates moneys in fund to Housing and Community Services Department to support fiduciary organizations development of individual development accounts. Modifies individual development account program and decouples program from sunset tax credit program.",
    "CurrentVersion": null,
    "RelatingToFull": "Relating to individual development accounts; creating new provisions; and amending ORS 315.650, 316.699, 458.670, 458.675, 458.680, 458.685, 458.690, 458.695 and 458.700.\n\t",
    "RelatingTo": "Relating to individual development accounts.",
    "AtTheRequestOf": "(at the request of Governor Kate Brown for Housing and Community Services Department)",
    "ChapterNumber": null,
    "CurrentLocation": "In Senate Committee",
    "CurrentCommitteeCode": "SHDEV",
    "CurrentSubCommittee": null,
    "FiscalImpact": "Fiscal impact issued",
    "RevenueImpact": "Has minimal revenue impact",
    "EmergencyClause": false,
    "EffectiveDate": null,
    "FiscalAnalyst": "Kim To",
    "RevenueEconomist": "Kyle Easton",
    "LCNumber": 688,
    "Vetoed": false,
    "CreatedDate": "2020-12-14T11:02:48",
    "ModifiedDate": "2021-06-28T08:58:12",
    "PrefixMeaning": "Senate Bill"
  },
  "sponsors": [
    {
      "MeasureSponsorId": "113163",
      "SessionKey": "2021R1",
      "MeasurePrefix": "SB",
      "MeasureNumber": 82,
      "SponsorType": "Presession",
      "LegislatoreCode": null,
      "CommitteeCode": null,
      "SponsorLevel": "Regular",
      "PrintOrder": "20",
      "PresessionFiledMessage": "Printed pursuant to Senate Interim Rule 213.28 by order of the President of the Senate in conformance with presession filing rules, indicating neither advocacy nor opposition on the part of the President.",
      "CreatedDate": "2021-01-09T19:30:57",
      "ModifiedDate": null
    }
  ],
  "historyActions": [
    {
      "MeasureHistoryId": 493175,
      "SessionKey": "2021R1",
      "MeasurePrefix": "SB",
      "MeasureNumber": 82,
      "Chamber": "S",
      "ActionDate": "2021-01-11T09:28:22",
      "ActionText": "Introduction and first reading. Referred to President's desk.",
      "VoteText": null,
      "CreatedDate": "2021-01-11T09:28:40",
      "ModifiedDate": null,
      "PublicNotification": true
    },
    {
      "MeasureHistoryId": 493998,
      "SessionKey": "2021R1",
      "MeasurePrefix": "SB",
      "MeasureNumber": 82,
      "Chamber": "S",
      "ActionDate": "2021-01-19T11:35:42",
      "ActionText": "Referred to Housing and Development, then Finance and Revenue.",
      "VoteText": null,
      "CreatedDate": "2021-01-19T11:36:34",
      "ModifiedDate": null,
      "PublicNotification": true
    },
    {
      "MeasureHistoryId": 497503,
      "SessionKey": "2021R1",
      "MeasurePrefix": "SB",
      "MeasureNumber": 82,
      "Chamber": "S",
      "ActionDate": "2021-02-04T13:01:00",
      "ActionText": "Public Hearing held.",
      "VoteText": null,
      "CreatedDate": "2021-02-04T14:48:31",
      "ModifiedDate": null,
      "PublicNotification": false
    },
    {
      "MeasureHistoryId": 536264,
      "SessionKey": "2021R1",
      "MeasurePrefix": "SB",
      "MeasureNumber": 82,
      "Chamber": "S",
      "ActionDate": "2021-06-26T17:37:00",
      "ActionText": "In committee upon adjournment.",
      "VoteText": null,
      "CreatedDate": "2021-07-06T13:57:54",
      "ModifiedDate": null,
      "PublicNotification": false
    }
  ],
  "documents": [
    {
      "SessionKey": "2021R1",
      "MeasurePrefix": "SB",
      "MeasureNumber": 82,
      "VersionDescription": "Introduced",
      "DocumentUrl": "https://olis.oregonlegislature.gov/liz/2021R1/Downloads/MeasureDocument/SB82/Introduced",
      "CreatedDate": "2021-01-10T08:18:36.61",
      "ModifiedDate": null
    }
  ],
  "testimony": [
    {
      "CommTestId": 628,
      "SubmitterFirstName": "Randy ",
      "SubmitterLastName": "Lucas",
      "BehalfOf": null,
      "Organization": "Portland",
      "DocumentDescription": "Testimony",
      "CreatedDate": "2021-02-01T09:54:52.773",
      "ModifiedDate": "2021-02-01T09:54:54.94",
      "PdfCreatedFlag": "Y",
      "PositionOnMeasureId": 3983,
      "SessionKey": "2021R1",
      "CommitteeCode": "SHDEV",
      "MeetingDate": "2021-02-04T13:00:00",
      "MeasurePrefix": "SB",
      "MeasureNumber": 82,
      "DocumentUrl": "https://olis.oregonlegislature.gov/liz/2021R1",
      "FirstName": null,
      "LastName": null,
      "ExecApptId": null,
      "Topic": "Establishes Individual Development Account Fund."
    },
    {
      "CommTestId": 708,
      "SubmitterFirstName": "Abigail",
      "SubmitterLastName": "Bowman",
      "BehalfOf": null,
      "Organization": "Portland ",
      "DocumentDescription": "Testimony",
      "CreatedDate": "2021-02-01T13:35:15.013",
      "ModifiedDate": "2021-02-01T14:08:10.733",
      "PdfCreatedFlag": "Y",
      "PositionOnMeasureId": 3983,
      "SessionKey": "2021R1",
      "CommitteeCode": "SHDEV",
      "MeetingDate": "2021-02-04T13:00:00",
      "MeasurePrefix": "SB",
      "MeasureNumber": 82,
      "DocumentUrl": "https://olis.oregonlegislature.gov/liz/2021R1",
      "FirstName": null,
      "LastName": null,
      "ExecApptId": null,
      "Topic": "Establishes Individual Development Account Fund."
    },
    {
      "CommTestId": 987,
      "SubmitterFirstName": "Marie",
      "SubmitterLastName": "Alaniz",
      "BehalfOf": "Northwest Housing Alternatives",
      "Organization": "Milwaukie",
      "DocumentDescription": "Photo",
      "CreatedDate": "2021-02-02T08:41:26.637",
      "ModifiedDate": null,
      "PdfCreatedFlag": "Y",
      "PositionOnMeasureId": 4022,
      "SessionKey": "2021R1",
      "CommitteeCode": "SHDEV",
      "MeetingDate": "2021-02-04T13:00:00",
      "MeasurePrefix": "SB",
      "MeasureNumber": 82,
      "DocumentUrl": "https://olis.oregonlegislature.gov/liz/2021R1",
      "FirstName": null,
      "LastName": null,
      "ExecApptId": null,
      "Topic": "Establishes Individual Development Account Fund."
    },
    {
      "CommTestId": 1015,
      "SubmitterFirstName": "Marie",
      "SubmitterLastName": "Alaniz",
      "BehalfOf": "Northwest Housing Alternatives",
      "Organization": "Milwaukie",
      "DocumentDescription": "Testimony",
      "CreatedDate": "2021-02-02T09:35:44.237",
      "ModifiedDate": "2021-02-02T09:46:08.78",
      "PdfCreatedFlag": "Y",
      "PositionOnMeasureId": 4022,
      "SessionKey": "2021R1",
      "CommitteeCode": "SHDEV",
      "MeetingDate": "2021-02-04T13:00:00",
      "MeasurePrefix": "SB",
      "MeasureNumber": 82,
      "DocumentUrl": "https://olis.oregonlegislature.gov/liz/2021R1",
      "FirstName": null,
      "LastName": null,
      "ExecApptId": null,
      "Topic": "Establishes Individual Development Account Fund."
    },
    {
      "CommTestId": 1026,
      "SubmitterFirstName": "BRIAN",
      "SubmitterLastName": "PARHAM",
      "BehalfOf": "The Ultimate Rock Guitar Dojo for Kids LLC",
      "Organization": "Portland",
      "DocumentDescription": "Testimony",
      "CreatedDate": "2021-02-02T10:07:54.757",
      "ModifiedDate": "2021-02-02T10:15:44.29",
      "PdfCreatedFlag": "Y",
      "PositionOnMeasureId": 3983,
      "SessionKey": "2021R1",
      "CommitteeCode": "SHDEV",
      "MeetingDate": "2021-02-04T13:00:00",
      "MeasurePrefix": "SB",
      "MeasureNumber": 82,
      "DocumentUrl": "https://olis.oregonlegislature.gov/liz/2021R1",
      "FirstName": null,
      "LastName": null,
      "ExecApptId": null,
      "Topic": "Establishes Individual Development Account Fund."
    },
    {
      "CommTestId": 1071,
      "SubmitterFirstName": "Helaine",
      "SubmitterLastName": "Koch",
      "BehalfOf": null,
      "Organization": "Food Roots",
      "DocumentDescription": "Testimony",
      "CreatedDate": "2021-02-02T11:52:01.3",
      "ModifiedDate": "2021-02-02T12:02:10.95",
      "PdfCreatedFlag": "Y",
      "PositionOnMeasureId": 3983,
      "SessionKey": "2021R1",
      "CommitteeCode": "SHDEV",
      "MeetingDate": "2021-02-04T13:00:00",
      "MeasurePrefix": "SB",
      "MeasureNumber": 82,
      "DocumentUrl": "https://olis.oregonlegislature.gov/liz/2021R1",
      "FirstName": null,
      "LastName": null,
      "ExecApptId": null,
      "Topic": "Establishes Individual Development Account Fund."
    },
    {
      "CommTestId": 1204,
      "SubmitterFirstName": "Lisa",
      "SubmitterLastName": "Dawson",
      "BehalfOf": null,
      "Organization": "Northeast Oregon Economic Development District",
      "DocumentDescription": "Testimony",
      "CreatedDate": "2021-02-02T16:53:06.52",
      "ModifiedDate": "2021-02-02T17:03:07.967",
      "PdfCreatedFlag": "Y",
      "PositionOnMeasureId": 3983,
      "SessionKey": "2021R1",
      "CommitteeCode": "SHDEV",
      "MeetingDate": "2021-02-04T13:00:00",
      "MeasurePrefix": "SB",
      "MeasureNumber": 82,
      "DocumentUrl": "https://olis.oregonlegislature.gov/liz/2021R1",
      "FirstName": null,
      "LastName": null,
      "ExecApptId": null,
      "Topic": "Establishes Individual Development Account Fund."
    },
    {
      "CommTestId": 1363,
      "SubmitterFirstName": "Michelle",
      "SubmitterLastName": "Scott",
      "BehalfOf": "Klamath Housing Auth",
      "Organization": "Klamath Falls",
      "DocumentDescription": "Testimony",
      "CreatedDate": "2021-02-03T09:55:01.623",
      "ModifiedDate": "2021-02-03T10:01:56.543",
      "PdfCreatedFlag": "Y",
      "PositionOnMeasureId": 3983,
      "SessionKey": "2021R1",
      "CommitteeCode": "SHDEV",
      "MeetingDate": "2021-02-04T13:00:00",
      "MeasurePrefix": "SB",
      "MeasureNumber": 82,
      "DocumentUrl": "https://olis.oregonlegislature.gov/liz/2021R1",
      "FirstName": null,
      "LastName": null,
      "ExecApptId": null,
      "Topic": "Establishes Individual Development Account Fund."
    },
    {
      "CommTestId": 1368,
      "SubmitterFirstName": "Marianna",
      "SubmitterLastName": "Thielen",
      "BehalfOf": null,
      "Organization": "Portland",
      "DocumentDescription": "Testimony",
      "CreatedDate": "2021-02-03T09:57:27.59",
      "ModifiedDate": "2021-02-03T09:57:28.41",
      "PdfCreatedFlag": "Y",
      "PositionOnMeasureId": 4022,
      "SessionKey": "2021R1",
      "CommitteeCode": "SHDEV",
      "MeetingDate": "2021-02-04T13:00:00",
      "MeasurePrefix": "SB",
      "MeasureNumber": 82,
      "DocumentUrl": "https://olis.oregonlegislature.gov/liz/2021R1",
      "FirstName": null,
      "LastName": null,
      "ExecApptId": null,
      "Topic": "Establishes Individual Development Account Fund."
    },
    {
      "CommTestId": 1418,
      "SubmitterFirstName": "Andrew",
      "SubmitterLastName": "Hall",
      "BehalfOf": "Families Forward",
      "Organization": "Redmond",
      "DocumentDescription": "Testimony",
      "CreatedDate": "2021-02-03T10:49:56.003",
      "ModifiedDate": "2021-02-03T10:49:56.953",
      "PdfCreatedFlag": "Y",
      "PositionOnMeasureId": 3983,
      "SessionKey": "2021R1",
      "CommitteeCode": "SHDEV",
      "MeetingDate": "2021-02-04T13:00:00",
      "MeasurePrefix": "SB",
      "MeasureNumber": 82,
      "DocumentUrl": "https://olis.oregonlegislature.gov/liz/2021R1",
      "FirstName": null,
      "LastName": null,
      "ExecApptId": null,
      "Topic": "Establishes Individual Development Account Fund."
    },
    {
      "CommTestId": 1598,
      "SubmitterFirstName": "Jeffrey",
      "SubmitterLastName": "Belzer",
      "BehalfOf": null,
      "Organization": "Bend",
      "DocumentDescription": "Testimony",
      "CreatedDate": "2021-02-03T16:01:44.8",
      "ModifiedDate": "2021-02-03T16:01:47.11",
      "PdfCreatedFlag": "Y",
      "PositionOnMeasureId": 3983,
      "SessionKey": "2021R1",
      "CommitteeCode": "SHDEV",
      "MeetingDate": "2021-02-04T13:00:00",
      "MeasurePrefix": "SB",
      "MeasureNumber": 82,
      "DocumentUrl": "https://olis.oregonlegislature.gov/liz/2021R1",
      "FirstName": null,
      "LastName": null,
      "ExecApptId": null,
      "Topic": "Establishes Individual Development Account Fund."
    },
    {
      "CommTestId": 1629,
      "SubmitterFirstName": "Nicole",
      "SubmitterLastName": "Stingh",
      "BehalfOf": "Andrea Bell",
      "Organization": "Oregon Housing and Community Services",
      "DocumentDescription": "Testimony",
      "CreatedDate": "2021-02-03T17:29:24.393",
      "ModifiedDate": "2021-02-04T07:57:58.723",
      "PdfCreatedFlag": "Y",
      "PositionOnMeasureId": 3983,
      "SessionKey": "2021R1",
      "CommitteeCode": "SHDEV",
      "MeetingDate": "2021-02-04T13:00:00",
      "MeasurePrefix": "SB",
      "MeasureNumber": 82,
      "DocumentUrl": "https://olis.oregonlegislature.gov/liz/2021R1",
      "FirstName": null,
      "LastName": null,
      "ExecApptId": null,
      "Topic": "Establishes Individual Development Account Fund."
    },
    {
      "CommTestId": 1632,
      "SubmitterFirstName": "Crystal",
      "SubmitterLastName": "Granger",
      "BehalfOf": null,
      "Organization": "Bradley Angle House",
      "DocumentDescription": "Testimony",
      "CreatedDate": "2021-02-03T17:36:33.683",
      "ModifiedDate": "2021-02-04T07:57:58.8",
      "PdfCreatedFlag": "Y",
      "PositionOnMeasureId": 3983,
      "SessionKey": "2021R1",
      "CommitteeCode": "SHDEV",
      "MeetingDate": "2021-02-04T13:00:00",
      "MeasurePrefix": "SB",
      "MeasureNumber": 82,
      "DocumentUrl": "https://olis.oregonlegislature.gov/liz/2021R1",
      "FirstName": null,
      "LastName": null,
      "ExecApptId": null,
      "Topic": "Establishes Individual Development Account Fund."
    },
    {
      "CommTestId": 1764,
      "SubmitterFirstName": "Lloyd",
      "SubmitterLastName": "Mueller",
      "BehalfOf": "Clatsop Community College",
      "Organization": "Astoria",
      "DocumentDescription": "Testimony",
      "CreatedDate": "2021-02-04T11:49:45.25",
      "ModifiedDate": "2021-02-04T11:58:32.04",
      "PdfCreatedFlag": "Y",
      "PositionOnMeasureId": 4022,
      "SessionKey": "2021R1",
      "CommitteeCode": "SHDEV",
      "MeetingDate": "2021-02-04T13:00:00",
      "MeasurePrefix": "SB",
      "MeasureNumber": 82,
      "DocumentUrl": "https://olis.oregonlegislature.gov/liz/2021R1",
      "FirstName": null,
      "LastName": null,
      "ExecApptId": null,
      "Topic": "Establishes Individual Development Account Fund."
    },
    {
      "CommTestId": 1783,
      "SubmitterFirstName": "Jody ",
      "SubmitterLastName": "Wiser",
      "BehalfOf": null,
      "Organization": "Tax Fairness Oregon",
      "DocumentDescription": "Testimony",
      "CreatedDate": "2021-02-04T12:43:15.09",
      "ModifiedDate": "2021-02-04T12:46:06.75",
      "PdfCreatedFlag": "Y",
      "PositionOnMeasureId": 3981,
      "SessionKey": "2021R1",
      "CommitteeCode": "SHDEV",
      "MeetingDate": "2021-02-04T13:00:00",
      "MeasurePrefix": "SB",
      "MeasureNumber": 82,
      "DocumentUrl": "https://olis.oregonlegislature.gov/liz/2021R1",
      "FirstName": null,
      "LastName": null,
      "ExecApptId": null,
      "Topic": "Establishes Individual Development Account Fund."
    },
    {
      "CommTestId": 1800,
      "SubmitterFirstName": "Suzanne",
      "SubmitterLastName": "Veaudry Casaus",
      "BehalfOf": "PCRI",
      "Organization": "Portland",
      "DocumentDescription": "Testimony",
      "CreatedDate": "2021-02-04T13:11:00.823",
      "ModifiedDate": "2021-02-04T13:29:14.39",
      "PdfCreatedFlag": "Y",
      "PositionOnMeasureId": 3983,
      "SessionKey": "2021R1",
      "CommitteeCode": "SHDEV",
      "MeetingDate": "2021-02-04T13:00:00",
      "MeasurePrefix": "SB",
      "MeasureNumber": 82,
      "DocumentUrl": "https://olis.oregonlegislature.gov/liz/2021R1",
      "FirstName": null,
      "LastName": null,
      "ExecApptId": null,
      "Topic": "Establishes Individual Development Account Fund."
    },
    {
      "CommTestId": 1927,
      "SubmitterFirstName": "David",
      "SubmitterLastName": "Wall",
      "BehalfOf": null,
      "Organization": "Newberg",
      "DocumentDescription": "Testimony",
      "CreatedDate": "2021-02-04T22:22:45.787",
      "ModifiedDate": "2021-02-05T08:22:36.75",
      "PdfCreatedFlag": "Y",
      "PositionOnMeasureId": 3982,
      "SessionKey": "2021R1",
      "CommitteeCode": "SHDEV",
      "MeetingDate": "2021-02-04T13:00:00",
      "MeasurePrefix": "SB",
      "MeasureNumber": 82,
      "DocumentUrl": "https://olis.oregonlegislature.gov/liz/2021R1",
      "FirstName": null,
      "LastName": null,
      "ExecApptId": null,
      "Topic": "Establishes Individual Development Account Fund."
    },
    {
      "CommTestId": 1935,
      "SubmitterFirstName": "Seth",
      "SubmitterLastName": "Weber",
      "BehalfOf": null,
      "Organization": "Portland",
      "DocumentDescription": "Testimony",
      "CreatedDate": "2021-02-05T07:37:20.057",
      "ModifiedDate": "2021-02-05T08:23:20.443",
      "PdfCreatedFlag": "Y",
      "PositionOnMeasureId": 3983,
      "SessionKey": "2021R1",
      "CommitteeCode": "SHDEV",
      "MeetingDate": "2021-02-04T13:00:00",
      "MeasurePrefix": "SB",
      "MeasureNumber": 82,
      "DocumentUrl": "https://olis.oregonlegislature.gov/liz/2021R1",
      "FirstName": null,
      "LastName": null,
      "ExecApptId": null,
      "Topic": "Establishes Individual Development Account Fund."
    },
    {
      "CommTestId": 1960,
      "SubmitterFirstName": "Miranda",
      "SubmitterLastName": "Mishan",
      "BehalfOf": "NAYA Family Center",
      "Organization": "Portland",
      "DocumentDescription": "Testimony",
      "CreatedDate": "2021-02-05T09:50:55.063",
      "ModifiedDate": "2021-02-05T10:12:33.64",
      "PdfCreatedFlag": "Y",
      "PositionOnMeasureId": 3983,
      "SessionKey": "2021R1",
      "CommitteeCode": "SHDEV",
      "MeetingDate": "2021-02-04T13:00:00",
      "MeasurePrefix": "SB",
      "MeasureNumber": 82,
      "DocumentUrl": "https://olis.oregonlegislature.gov/liz/2021R1",
      "FirstName": null,
      "LastName": null,
      "ExecApptId": null,
      "Topic": "Establishes Individual Development Account Fund."
    },
    {
      "CommTestId": 1980,
      "SubmitterFirstName": "Nicole",
      "SubmitterLastName": "Stingh",
      "BehalfOf": null,
      "Organization": "Oregon Housing and Community Services",
      "DocumentDescription": "Testimony",
      "CreatedDate": "2021-02-05T11:38:09.183",
      "ModifiedDate": "2021-02-05T13:11:42.797",
      "PdfCreatedFlag": "Y",
      "PositionOnMeasureId": 3983,
      "SessionKey": "2021R1",
      "CommitteeCode": "SHDEV",
      "MeetingDate": "2021-02-04T13:00:00",
      "MeasurePrefix": "SB",
      "MeasureNumber": 82,
      "DocumentUrl": "https://olis.oregonlegislature.gov/liz/2021R1",
      "FirstName": null,
      "LastName": null,
      "ExecApptId": null,
      "Topic": "Establishes Individual Development Account Fund."
    },
    {
      "CommTestId": 3032,
      "SubmitterFirstName": "Loren",
      "SubmitterLastName": "Naldoza",
      "BehalfOf": null,
      "Organization": "Neighborhood Partnerships",
      "DocumentDescription": "Testimony",
      "CreatedDate": "2021-02-10T13:22:03.64",
      "ModifiedDate": null,
      "PdfCreatedFlag": "Y",
      "PositionOnMeasureId": 4022,
      "SessionKey": "2021R1",
      "CommitteeCode": "SHDEV",
      "MeetingDate": "2021-02-04T13:00:00",
      "MeasurePrefix": "SB",
      "MeasureNumber": 82,
      "DocumentUrl": "https://olis.oregonlegislature.gov/liz/2021R1",
      "FirstName": null,
      "LastName": null,
      "ExecApptId": null,
      "Topic": "Establishes Individual Development Account Fund."
    }
  ]
}