{
  "measure": {
    "SessionKey": "2019R1",
    "MeasurePrefix": "HB",
    "MeasureNumber": 2596,
    "CatchLine": "Allows cities and counties to impose controls on rental rates and rental rate increases applicable to spaces in facilities for manufactured or floating homes.",
    "MinorityCatchLine": null,
    "MeasureSummary": "\tAllows cities and counties to impose controls on rental rates and rental rate increases applicable to spaces in facilities for manufactured or floating homes.",
    "CurrentVersion": null,
    "RelatingToFull": "Relating to local rent control of spaces in a facility; creating new provisions; and amending ORS 91.225.",
    "RelatingTo": "Relating to local rent control of spaces in a facility.",
    "AtTheRequestOf": null,
    "ChapterNumber": null,
    "CurrentLocation": "In House Committee",
    "CurrentCommitteeCode": "HHS",
    "CurrentSubCommittee": null,
    "FiscalImpact": "May have fiscal impact, but no statement yet issued",
    "RevenueImpact": "May have revenue impact, but no statement yet issued",
    "EmergencyClause": false,
    "EffectiveDate": null,
    "FiscalAnalyst": "Krista Dauenhauer",
    "RevenueEconomist": "Chris Allanach",
    "LCNumber": 1898,
    "Vetoed": false,
    "CreatedDate": "2018-12-20T16:11:46",
    "ModifiedDate": "2020-06-26T19:41:22",
    "PrefixMeaning": "House Bill"
  },
  "sponsors": [
    {
      "MeasureSponsorId": "94173",
      "SessionKey": "2019R1",
      "MeasurePrefix": "HB",
      "MeasureNumber": 2596,
      "SponsorType": "Presession",
      "LegislatoreCode": null,
      "CommitteeCode": null,
      "SponsorLevel": "Regular",
      "PrintOrder": "20",
      "PresessionFiledMessage": "(Presession filed.)",
      "CreatedDate": "2019-01-09T14:55:43",
      "ModifiedDate": null
    },
    {
      "MeasureSponsorId": "94174",
      "SessionKey": "2019R1",
      "MeasurePrefix": "HB",
      "MeasureNumber": 2596,
      "SponsorType": "Member",
      "LegislatoreCode": "Rep Fahey",
      "CommitteeCode": null,
      "SponsorLevel": "Chief",
      "PrintOrder": "1",
      "PresessionFiledMessage": null,
      "CreatedDate": "2019-01-09T14:55:43",
      "ModifiedDate": null
    }
  ],
  "historyActions": [
    {
      "MeasureHistoryId": 438101,
      "SessionKey": "2019R1",
      "MeasurePrefix": "HB",
      "MeasureNumber": 2596,
      "Chamber": "H",
      "ActionDate": "2019-01-14T08:54:51",
      "ActionText": "First reading. Referred to Speaker's desk.",
      "VoteText": null,
      "CreatedDate": "2019-01-14T08:55:40",
      "ModifiedDate": null,
      "PublicNotification": false
    },
    {
      "MeasureHistoryId": 439210,
      "SessionKey": "2019R1",
      "MeasurePrefix": "HB",
      "MeasureNumber": 2596,
      "Chamber": "H",
      "ActionDate": "2019-01-15T15:56:58",
      "ActionText": "Referred to Human Services and Housing.",
      "VoteText": null,
      "CreatedDate": "2019-01-15T16:00:08",
      "ModifiedDate": null,
      "PublicNotification": false
    },
    {
      "MeasureHistoryId": 481417,
      "SessionKey": "2019R1",
      "MeasurePrefix": "HB",
      "MeasureNumber": 2596,
      "Chamber": "H",
      "ActionDate": "2019-06-30T17:23:00",
      "ActionText": "In committee upon adjournment.",
      "VoteText": null,
      "CreatedDate": "2019-07-08T16:02:18",
      "ModifiedDate": null,
      "PublicNotification": false
    }
  ],
  "documents": [
    {
      "SessionKey": "2019R1",
      "MeasurePrefix": "HB",
      "MeasureNumber": 2596,
      "VersionDescription": "Introduced",
      "DocumentUrl": "https://olis.oregonlegislature.gov/liz/2019R1/Downloads/MeasureDocument/HB2596/Introduced",
      "CreatedDate": "2019-01-09T20:27:14.243",
      "ModifiedDate": null
    }
  ],
  "testimony": []
}